src/__init__.py
src/testproject/__init__.py
src/testproject/definitions.py
src/testproject/classes/__init__.py
src/testproject/classes/actionexecutionresponse.py
src/testproject/classes/driver_step_settings.py
src/testproject/classes/elementsearchcriteria.py
src/testproject/classes/proxydescriptor.py
src/testproject/classes/resultfield.py
src/testproject/classes/step_settings.py
src/testproject/classes/web_driver_wait.py
src/testproject/decorator/__init__.py
src/testproject/decorator/behave_reporter.py
src/testproject/decorator/pytestBDD_reporter.py
src/testproject/decorator/report.py
src/testproject/decorator/report_assertion_errors.py
src/testproject/enums/__init__.py
src/testproject/enums/environmentvariable.py
src/testproject/enums/executionfailuretype.py
src/testproject/enums/executionresulttype.py
src/testproject/enums/findbytype.py
src/testproject/enums/report_type.py
src/testproject/enums/reportnamingelement.py
src/testproject/enums/screenshot_condition_type.py
src/testproject/enums/sleep_timing_type.py
src/testproject/executionresults/__init__.py
src/testproject/executionresults/operationresult.py
src/testproject/helpers/__init__.py
src/testproject/helpers/activesessionhelper.py
src/testproject/helpers/addonhelper.py
src/testproject/helpers/confighelper.py
src/testproject/helpers/logginghelper.py
src/testproject/helpers/reporthelper.py
src/testproject/helpers/seleniumhelper.py
src/testproject/helpers/step_helper.py
src/testproject/rest/__init__.py
src/testproject/rest/reportsettings.py
src/testproject/rest/messages/__init__.py
src/testproject/rest/messages/addonexecutionresponse.py
src/testproject/rest/messages/agentstatusresponse.py
src/testproject/rest/messages/customtestreport.py
src/testproject/rest/messages/drivercommandreport.py
src/testproject/rest/messages/reportitemtype.py
src/testproject/rest/messages/sessionrequest.py
src/testproject/rest/messages/sessionresponse.py
src/testproject/rest/messages/stepreport.py
src/testproject/sdk/__init__.py
testproject_python_sdk-1.2.3.dist-info/LICENSE
testproject_python_sdk-1.2.3.dist-info/METADATA
testproject_python_sdk-1.2.3.dist-info/WHEEL
testproject_python_sdk-1.2.3.dist-info/top_level.txt
testproject_python_sdk-1.2.3.dist-info/RECORD
