Metadata-Version: 2.1
Name: testproject-python-sdk
Version: 1.2.3
Summary: Selenium and Appium powered SDK for TestProject.io
Home-page: https://github.com/testproject-io/python-opensdk
Author: TestProject
Author-email: contact@testproject.io
License: UNKNOWN
Platform: UNKNOWN
Classifier: Programming Language :: Python :: 3
Classifier: License :: OSI Approved :: Apache Software License
Classifier: Operating System :: OS Independent
Requires-Python: >=3.6
License-File: LICENSE
Requires-Dist: selenium (==3.141.0)
Requires-Dist: Appium-Python-Client (<=1.0.2,>=1.0.1)
Requires-Dist: decorator (>=4.4.2)
Requires-Dist: requests (>=2.24.0)
Requires-Dist: importlib-metadata (>=1.7.0)
Requires-Dist: packaging (>=20.4)
